{"accessibilityPrompt":true,"alwaysOnTop":false,"appVersion":"1","arch":"x64","asar":false,"blockExternalUrls":false,"bounce":false,"buildDate":1667797937982,"clearCache":false,"counter":false,"darwinDarkModeSupport":false,"disableContextMenu":false,"disableDevTools":false,"disableGpu":false,"disableOldBuildWarning":false,"electronVersionUsed":"19.0.17","enableEs3Apis":false,"fastQuit":false,"fullScreen":false,"height":800,"hideWindowFrame":false,"ignoreCertificate":false,"ignoreGpuBlacklist":false,"insecure":false,"isUpgrade":false,"maximize":false,"name":"YouTube Electron","nativefierVersion":"50.0.0","portable":true,"quiet":false,"showMenuBar":false,"singleInstance":false,"strictInternalUrls":false,"targetUrl":"https://youtube.com/","tray":"false","userAgent":"Mozilla/5.0 (Windows NT 10.0; Win64; x64; rv:106.0.5) Gecko/20100101 Firefox/106.0.5","userAgentHonest":false,"width":1280,"widevine":false,"win32metadata":{"ProductName":"YouTube Electron","InternalName":"YouTube Electron","FileDescription":"YouTube Electron"},"zoom":1,"oldBuildWarningText":""}